videofeatures/ActivityNetDatasetProvider.py
videofeatures/BaseFeatureExtractor.py
videofeatures/CNNFeatures.py
videofeatures/CVFeatures.py
videofeatures/TwentyBNDatasetProvider.py
videofeatures/__init__.py
videofeatures/videofeatures.py
videofeatures-0.2.dist-info/DESCRIPTION.rst
videofeatures-0.2.dist-info/METADATA
videofeatures-0.2.dist-info/RECORD
videofeatures-0.2.dist-info/WHEEL
videofeatures-0.2.dist-info/metadata.json
videofeatures-0.2.dist-info/top_level.txt
