Metadata-Version: 2.0
Name: videofeatures
Version: 0.2
Summary: Feature extraction from video or image (ResNet, VGG, SIFT, SURF) and training of a Fisher Vector GMM to compute (improved) Fisher Vectors
Home-page: https://github.com/jonasrothfuss/python-image-video-features
Author: Jonas Rothfuss, Fabio Ferreira
Author-email: fabioferreira@mailbox.org
License: MIT
Platform: UNKNOWN
Requires-Dist: numpy
Requires-Dist: scikit-learn
Requires-Dist: fishervector
Requires-Dist: keras
Requires-Dist: pandas
Requires-Dist: opencv-python
Requires-Dist: gulpio
